Rangebi/Rangebi.py
Rangebi/__init__.py
Rangebi/__main__.py
Rangebi/example.py
Rangebi-0.0.1.dist-info/DESCRIPTION.rst
Rangebi-0.0.1.dist-info/METADATA
Rangebi-0.0.1.dist-info/RECORD
Rangebi-0.0.1.dist-info/WHEEL
Rangebi-0.0.1.dist-info/metadata.json
Rangebi-0.0.1.dist-info/top_level.txt
