Metadata-Version: 2.0
Name: Rangebi
Version: 0.0.1
Summary: A mixed wrapper over coloroma, halo and pretty tables for building beautiful python cli applications.
Home-page: https://github.com/2658labs/Rangebi
Author: 2658 labs
Author-email: aspraz2658@gmail.com
License: MIT
Keywords: coloroma,colors in python,python,Rangebi
Platform: UNKNOWN
Requires-Python: >=3.5
Requires-Dist: colorama
Requires-Dist: halo
Requires-Dist: prettytable
